tellmejokes.py
tellmejokes-0.1.1.dist-info/entry_points.txt
tellmejokes-0.1.1.dist-info/METADATA
tellmejokes-0.1.1.dist-info/WHEEL
tellmejokes-0.1.1.dist-info/RECORD
